README.md
pyproject.toml
setup.py
./CLASS_rename.py
./CPU.py
./Makefile
./__init__.py
./external/.DS_Store
./external/HMcode/hmcode.c
./external/HMcode/hmcode.h
./external/Halofit/halofit.c
./external/Halofit/halofit.h
./external/HyRec2020/Alpha_inf.dat
./external/HyRec2020/README.md
./external/HyRec2020/R_inf.dat
./external/HyRec2020/energy_injection.c
./external/HyRec2020/energy_injection.h
./external/HyRec2020/fit_swift.dat
./external/HyRec2020/helium.c
./external/HyRec2020/helium.h
./external/HyRec2020/history.c
./external/HyRec2020/history.h
./external/HyRec2020/hydrogen.c
./external/HyRec2020/hydrogen.h
./external/HyRec2020/hyrec.c
./external/HyRec2020/hyrectools.c
./external/HyRec2020/hyrectools.h
./external/HyRec2020/input.dat
./external/HyRec2020/output_xe.dat
./external/HyRec2020/readme.pdf
./external/HyRec2020/two_photon_tables.dat
./external/HyRec2020/two_photon_tables_hires.dat
./external/HyRec2020/wrap_hyrec.c
./external/HyRec2020/wrap_hyrec.h
./external/RecfastCLASS/wrap_recfast.c
./external/RecfastCLASS/wrap_recfast.h
./external/bbn/sBBN.dat
./external/bbn/sBBN_2017.dat
./external/bbn/sBBN_2017_marcucci.dat
./external/bbn/sBBN_2025.dat
./external/bbn/sBBN_2025_primat.dat
./external/distortions/FIRAS_branching_ratios.dat
./external/distortions/FIRAS_distortions_shapes.dat
./external/distortions/FIRAS_nu_delta_I.dat
./external/distortions/Greens_data.dat
./external/distortions/PIXIE_branching_ratios.dat
./external/distortions/PIXIE_distortions_shapes.dat
./external/distortions/README
./external/distortions/detectors_list.dat
./external/distortions/generate_PCA_files.py
./external/external_Pk/Pk_example.dat
./external/external_Pk/Pk_example_w_tensors.dat
./external/external_Pk/README.md
./external/external_Pk/generate_Pk_example.py
./external/external_Pk/generate_Pk_example_w_tensors.py
./external/heating/Galli_et_al_2013.dat
./external/heating/README
./external/heating/example_chix_file.dat
./external/heating/example_chiz_file.dat
classy.egg-info/PKG-INFO
classy.egg-info/SOURCES.txt
classy.egg-info/dependency_links.txt
classy.egg-info/not-zip-safe
classy.egg-info/top_level.txt
