Metadata-Version: 2.1
Name: classy
Version: 3.3.3.0
Summary: Python interface to the Cosmological Boltzmann code CLASS
Home-page: http://www.class-code.net
Author: Julien Lesgourgues, Thomas Tram, Nils Schöneberg, ... and many more (see webpage)
Project-URL: Homepage, http://www.class-code.net
